llama_index/tools/text_to_image/__init__.py
llama_index/tools/text_to_image/base.py
llama_index_tools_text_to_image-0.4.1.dist-info/METADATA
llama_index_tools_text_to_image-0.4.1.dist-info/WHEEL
llama_index_tools_text_to_image-0.4.1.dist-info/licenses/LICENSE
llama_index_tools_text_to_image-0.4.1.dist-info/RECORD
