Metadata-Version: 2.4
Name: llama-index-tools-text-to-image
Version: 0.4.1
Summary: llama-index tools text_to_image integration
Author-email: Your Name <you@example.com>
Maintainer: ajhofmann
License-Expression: MIT
License-File: LICENSE
Requires-Python: <4.0,>=3.9
Requires-Dist: llama-index-core<0.15,>=0.13.0
Requires-Dist: matplotlib<4,>=3.8.2
Requires-Dist: openai>=1.1.0
Requires-Dist: pillow<11,>=10.2.0
